sqlalchemy_query_helper/__init__.py
sqlalchemy_query_helper/query_generator.py
tests/__init__.py
tests/model.py
tests/test_query_generator.py
sqlalchemy_query_helper-0.0.5.dist-info/METADATA
sqlalchemy_query_helper-0.0.5.dist-info/WHEEL
sqlalchemy_query_helper-0.0.5.dist-info/top_level.txt
sqlalchemy_query_helper-0.0.5.dist-info/RECORD
